{
  "accountAssociation": {
    "header": "eyJmaWQiOjY1MzQ3OSwidHlwZSI6ImF1dGgiLCJrZXkiOiIweDFFNmY4NGYyMzA1MTZlNDM1MTkwNkY1YkIxRjZiNDJBOTkzNThlNzIifQ",
    "payload": "eyJkb21haW4iOiJjZWxvcmVtaXQudmVyY2VsLmFwcCJ9",
    "signature": "o+KxJG7fh6c9mBvJbn8w9qkED/hc4J/3Zy/M97+EZxtvX+/G9FlpVaN0ptTji/00Vd47OfYXMIU+0REZ1RTrLRw="
  },
  "frame": {
    "version": "1",
    "name": "CeloRemit",
    "iconUrl": "https://celoremit.vercel.app/icon.png",
    "homeUrl": "https://celoremit.vercel.app",
    "imageUrl": "https://celoremit.vercel.app/og-image.png",
    "splashImageUrl": "https://celoremit.vercel.app/splash.png",
    "splashBackgroundColor": "#0D4A3C",
    "buttonTitle": "💸 Send Money",
    "webhookUrl": "https://celoremit.vercel.app/api/webhook",
    "subtitle": "AI-Powered Remittances",
    "description": "Send money globally using natural language with 15 Mento stablecoins. Instant, low-fee remittances across Africa, Asia, Americas, and Europe powered by AI.",
    "screenshotUrls": [
      "https://celoremit.vercel.app/og-image.png"
    ],
    "primaryCategory": "finance",
    "tags": ["remittance", "payments", "celo", "stablecoins", "ai"],
    "heroImageUrl": "https://celoremit.vercel.app/og-image.png",
    "tagline": "Send money globally with AI",
    "ogTitle": "CeloRemit AI Remittances",
    "ogDescription": "Send money globally using natural language. 15 Mento stablecoins. Low fees, instant settlement.",
    "ogImageUrl": "https://celoremit.vercel.app/og-image.png",
    "castShareUrl": "https://celoremit.vercel.app"
  }
}
